.coveragerc
.gitignore
LICENSE
README.md
setup.py
.github/workflows/python-package.yml
difile/__init__.py
difile/cli.py
difile/core.py
difile.egg-info/PKG-INFO
difile.egg-info/SOURCES.txt
difile.egg-info/dependency_links.txt
difile.egg-info/entry_points.txt
difile.egg-info/requires.txt
difile.egg-info/top_level.txt
tests/test_smoke.py
tests/dirs/dir1/file1.txt
tests/dirs/dir1/file2.txt
tests/dirs/dir1/will_be_remove
tests/dirs/dir1/inner/file3.txt
tests/dirs/dir1/removed/a1
tests/dirs/dir1/removed/removed/a
tests/dirs/dir2/file1.txt
tests/dirs/dir2/file2.txt
tests/dirs/dir2/inner/file3.txt
tests/dirs/dir2/new/b
tests/dirs/dir2/new/new/b